README.rst
setup.py
cliauth/__init__.py
cliauth/management/__init__.py
cliauth/management/commands/__init__.py
cliauth/management/commands/cliauth.py
django_cliauth.egg-info/PKG-INFO
django_cliauth.egg-info/SOURCES.txt
django_cliauth.egg-info/dependency_links.txt
django_cliauth.egg-info/requires.txt
django_cliauth.egg-info/top_level.txt