Metadata-Version: 1.0
Name: django-cliauth
Version: 0.9.1
Summary: Authenticate Apache2 (basic auth) using your Django DB
Home-page: https://bitbucket.org/seocam/django-cliauth
Author: Sergio Oliveira
Author-email: seocam@seocam.com
License: GPL2
Platform: UNKNOWN
